{"nodes": [{"id": "users_arnold_jarvis_src_lib_crc32_cpp", "label": "crc32.cpp", "file_type": "code", "source_file": "src/lib/crc32.cpp", "source_location": "L1"}, {"id": "users_arnold_jarvis_src_lib_crc32_crc32_init", "label": "CRC32::init()", "file_type": "code", "source_file": "src/lib/crc32.cpp", "source_location": "L26", "_callable": true}, {"id": "users_arnold_jarvis_src_lib_crc32_crc32_update", "label": "CRC32::update()", "file_type": "code", "source_file": "src/lib/crc32.cpp", "source_location": "L42", "_callable": true}, {"id": "users_arnold_jarvis_src_lib_crc32_crc32_finalize", "label": "CRC32::finalize()", "file_type": "code", "source_file": "src/lib/crc32.cpp", "source_location": "L49", "_callable": true}], "edges": [{"source": "users_arnold_jarvis_src_lib_crc32_cpp", "target": "crc32", "relation": "imports", "context": "import", "confidence": "EXTRACTED", "source_file": "src/lib/crc32.cpp", "source_location": "L19", "weight": 1.0}, {"source": "users_arnold_jarvis_src_lib_crc32_cpp", "target": "users_arnold_jarvis_src_lib_crc32_crc32_init", "relation": "contains", "confidence": "EXTRACTED", "source_file": "src/lib/crc32.cpp", "source_location": "L26", "weight": 1.0}, {"source": "users_arnold_jarvis_src_lib_crc32_cpp", "target": "users_arnold_jarvis_src_lib_crc32_crc32_update", "relation": "contains", "confidence": "EXTRACTED", "source_file": "src/lib/crc32.cpp", "source_location": "L42", "weight": 1.0}, {"source": "users_arnold_jarvis_src_lib_crc32_cpp", "target": "users_arnold_jarvis_src_lib_crc32_crc32_finalize", "relation": "contains", "confidence": "EXTRACTED", "source_file": "src/lib/crc32.cpp", "source_location": "L49", "weight": 1.0}], "raw_calls": []}